{
  "Flasher": {
    "height": 148.0,
    "pos_x": 302.94952,
    "pos_y": 696.1246,
    "rot_x": -40.0,
    "rot_y": 0.0,
    "rot_z": 0.0,
    "color": "#ffffff",
    "is_timer_enabled": false,
    "timer_interval": 30,
    "name": "Flasherflash17",
    "image_a": "domeredflash",
    "image_b": "",
    "alpha": 5000,
    "modulate_vs_add": 0.8,
    "is_visible": false,
    "add_blend": true,
    "is_dmd": false,
    "display_texture": false,
    "depth_bias": 0.0,
    "image_alignment": "wrap",
    "filter": "multiply",
    "filter_amount": 1500,
    "light_map": null,
    "drag_points": [
      {
        "x": 220.29422,
        "y": 619.92944,
        "z": 0.0,
        "smooth": false,
        "is_slingshot": false,
        "has_auto_texture": true,
        "tex_coord": 0.0,
        "is_locked": false,
        "editor_layer": 0,
        "editor_layer_name": "",
        "editor_layer_visibility": true
      },
      {
        "x": 220.29422,
        "y": 772.3197,
        "z": 0.0,
        "smooth": false,
        "is_slingshot": false,
        "has_auto_texture": true,
        "tex_coord": 0.0,
        "is_locked": false,
        "editor_layer": 0,
        "editor_layer_name": "",
        "editor_layer_visibility": true
      },
      {
        "x": 385.60483,
        "y": 772.3194,
        "z": 0.0,
        "smooth": false,
        "is_slingshot": false,
        "has_auto_texture": true,
        "tex_coord": 0.0,
        "is_locked": false,
        "editor_layer": 0,
        "editor_layer_name": "",
        "editor_layer_visibility": true
      },
      {
        "x": 385.60483,
        "y": 619.92944,
        "z": 0.0,
        "smooth": false,
        "is_slingshot": false,
        "has_auto_texture": true,
        "tex_coord": 0.0,
        "is_locked": false,
        "editor_layer": 0,
        "editor_layer_name": "",
        "editor_layer_visibility": true
      }
    ]
  }
}