{
  "Light": {
    "center": {
      "x": 200.62872,
      "y": 1791.2496
    },
    "height": null,
    "falloff_radius": 0.01,
    "falloff_power": 2.0,
    "state_u32": 0,
    "state": null,
    "color": "#ffffff",
    "color2": "#ffffff",
    "is_timer_enabled": false,
    "timer_interval": 100,
    "blink_pattern": "01",
    "off_image": "playfield-4k",
    "blink_interval": 125,
    "intensity": 10.0,
    "transmission_scale": 0.5,
    "surface": "",
    "name": "LALLCAPS10",
    "is_backglass": false,
    "depth_bias": 0.0,
    "fade_speed_up": 3.0,
    "fade_speed_down": 1.0,
    "is_bulb_light": false,
    "is_image_mode": false,
    "show_bulb_mesh": false,
    "has_static_bulb_mesh": true,
    "show_reflection_on_ball": false,
    "mesh_radius": 20.0,
    "bulb_modulate_vs_add": 0.9,
    "bulb_halo_height": 28.0,
    "shadows": null,
    "fader": null,
    "visible": null,
    "drag_points": [
      {
        "x": 200.39452,
        "y": 1778.2107,
        "z": 0.0,
        "smooth": false,
        "is_slingshot": true,
        "has_auto_texture": true,
        "tex_coord": 0.0,
        "is_locked": false,
        "editor_layer": 0,
        "editor_layer_name": "",
        "editor_layer_visibility": true
      },
      {
        "x": 187.16202,
        "y": 1796.2781,
        "z": 0.0,
        "smooth": false,
        "is_slingshot": false,
        "has_auto_texture": true,
        "tex_coord": 0.0,
        "is_locked": false,
        "editor_layer": 0,
        "editor_layer_name": "",
        "editor_layer_visibility": true
      },
      {
        "x": 193.54926,
        "y": 1801.5265,
        "z": 0.0,
        "smooth": true,
        "is_slingshot": false,
        "has_auto_texture": true,
        "tex_coord": 0.0,
        "is_locked": false,
        "editor_layer": 0,
        "editor_layer_name": "",
        "editor_layer_visibility": true
      },
      {
        "x": 199.55856,
        "y": 1804.4618,
        "z": 0.0,
        "smooth": false,
        "is_slingshot": true,
        "has_auto_texture": true,
        "tex_coord": 0.0,
        "is_locked": false,
        "editor_layer": 0,
        "editor_layer_name": "",
        "editor_layer_visibility": true
      },
      {
        "x": 204.03828,
        "y": 1803.482,
        "z": 0.0,
        "smooth": true,
        "is_slingshot": false,
        "has_auto_texture": true,
        "tex_coord": 0.0,
        "is_locked": false,
        "editor_layer": 0,
        "editor_layer_name": "",
        "editor_layer_visibility": true
      },
      {
        "x": 206.48135,
        "y": 1801.7142,
        "z": 0.0,
        "smooth": false,
        "is_slingshot": true,
        "has_auto_texture": true,
        "tex_coord": 0.0,
        "is_locked": false,
        "editor_layer": 0,
        "editor_layer_name": "",
        "editor_layer_visibility": true
      },
      {
        "x": 207.6149,
        "y": 1796.9015,
        "z": 0.0,
        "smooth": false,
        "is_slingshot": false,
        "has_auto_texture": true,
        "tex_coord": 0.0,
        "is_locked": false,
        "editor_layer": 0,
        "editor_layer_name": "",
        "editor_layer_visibility": true
      },
      {
        "x": 206.33325,
        "y": 1793.4901,
        "z": 0.0,
        "smooth": true,
        "is_slingshot": false,
        "has_auto_texture": true,
        "tex_coord": 0.0,
        "is_locked": false,
        "editor_layer": 0,
        "editor_layer_name": "",
        "editor_layer_visibility": true
      },
      {
        "x": 209.4082,
        "y": 1793.3641,
        "z": 0.0,
        "smooth": true,
        "is_slingshot": false,
        "has_auto_texture": true,
        "tex_coord": 0.0,
        "is_locked": false,
        "editor_layer": 0,
        "editor_layer_name": "",
        "editor_layer_visibility": true
      },
      {
        "x": 212.30098,
        "y": 1790.8444,
        "z": 0.0,
        "smooth": false,
        "is_slingshot": true,
        "has_auto_texture": true,
        "tex_coord": 0.0,
        "is_locked": false,
        "editor_layer": 0,
        "editor_layer_name": "",
        "editor_layer_visibility": true
      },
      {
        "x": 211.84004,
        "y": 1786.0652,
        "z": 0.0,
        "smooth": true,
        "is_slingshot": false,
        "has_auto_texture": true,
        "tex_coord": 0.0,
        "is_locked": false,
        "editor_layer": 0,
        "editor_layer_name": "",
        "editor_layer_visibility": true
      },
      {
        "x": 206.79837,
        "y": 1781.9197,
        "z": 0.0,
        "smooth": false,
        "is_slingshot": true,
        "has_auto_texture": true,
        "tex_coord": 0.0,
        "is_locked": false,
        "editor_layer": 0,
        "editor_layer_name": "",
        "editor_layer_visibility": true
      }
    ]
  }
}