{
  "Light": {
    "center": {
      "x": 230.18079,
      "y": 1811.8121
    },
    "height": 0.0,
    "falloff_radius": 0.01,
    "falloff_power": 2.0,
    "state_u32": 0,
    "state": 0.0,
    "color": "#ffffff",
    "color2": "#ffffff",
    "is_timer_enabled": false,
    "timer_interval": 100,
    "blink_pattern": "01",
    "off_image": "playfield-4k",
    "blink_interval": 125,
    "intensity": 10.0,
    "transmission_scale": 0.5,
    "surface": "",
    "name": "LALLCAPS12",
    "is_backglass": false,
    "depth_bias": 0.0,
    "fade_speed_up": 3.0,
    "fade_speed_down": 1.0,
    "is_bulb_light": false,
    "is_image_mode": false,
    "show_bulb_mesh": false,
    "has_static_bulb_mesh": true,
    "show_reflection_on_ball": false,
    "mesh_radius": 20.0,
    "bulb_modulate_vs_add": 0.9,
    "bulb_halo_height": 28.0,
    "shadows": "none",
    "fader": "linear",
    "visible": true,
    "drag_points": [
      {
        "x": 229.55644,
        "y": 1799.8656,
        "z": 0.0,
        "smooth": false,
        "is_slingshot": true,
        "has_auto_texture": true,
        "tex_coord": 0.0,
        "is_locked": false,
        "editor_layer": 0,
        "editor_layer_name": "",
        "editor_layer_visibility": true
      },
      {
        "x": 216.24593,
        "y": 1817.5428,
        "z": 0.0,
        "smooth": false,
        "is_slingshot": false,
        "has_auto_texture": true,
        "tex_coord": 0.0,
        "is_locked": false,
        "editor_layer": 0,
        "editor_layer_name": "",
        "editor_layer_visibility": true
      },
      {
        "x": 221.39627,
        "y": 1821.299,
        "z": 0.0,
        "smooth": false,
        "is_slingshot": true,
        "has_auto_texture": true,
        "tex_coord": 0.0,
        "is_locked": false,
        "editor_layer": 0,
        "editor_layer_name": "",
        "editor_layer_visibility": true
      },
      {
        "x": 224.42746,
        "y": 1817.0209,
        "z": 0.0,
        "smooth": false,
        "is_slingshot": true,
        "has_auto_texture": true,
        "tex_coord": 0.0,
        "is_locked": false,
        "editor_layer": 0,
        "editor_layer_name": "",
        "editor_layer_visibility": true
      },
      {
        "x": 226.82515,
        "y": 1825.5544,
        "z": 0.0,
        "smooth": false,
        "is_slingshot": true,
        "has_auto_texture": true,
        "tex_coord": 0.0,
        "is_locked": false,
        "editor_layer": 0,
        "editor_layer_name": "",
        "editor_layer_visibility": true
      },
      {
        "x": 232.90565,
        "y": 1824.5631,
        "z": 0.0,
        "smooth": false,
        "is_slingshot": false,
        "has_auto_texture": true,
        "tex_coord": 0.0,
        "is_locked": false,
        "editor_layer": 0,
        "editor_layer_name": "",
        "editor_layer_visibility": true
      },
      {
        "x": 230.68216,
        "y": 1817.5039,
        "z": 0.0,
        "smooth": false,
        "is_slingshot": true,
        "has_auto_texture": true,
        "tex_coord": 0.0,
        "is_locked": false,
        "editor_layer": 0,
        "editor_layer_name": "",
        "editor_layer_visibility": true
      },
      {
        "x": 234.20161,
        "y": 1817.932,
        "z": 0.0,
        "smooth": false,
        "is_slingshot": false,
        "has_auto_texture": true,
        "tex_coord": 0.0,
        "is_locked": false,
        "editor_layer": 0,
        "editor_layer_name": "",
        "editor_layer_visibility": true
      },
      {
        "x": 237.94028,
        "y": 1816.603,
        "z": 0.0,
        "smooth": true,
        "is_slingshot": false,
        "has_auto_texture": true,
        "tex_coord": 0.0,
        "is_locked": false,
        "editor_layer": 0,
        "editor_layer_name": "",
        "editor_layer_visibility": true
      },
      {
        "x": 240.25548,
        "y": 1814.9891,
        "z": 0.0,
        "smooth": true,
        "is_slingshot": false,
        "has_auto_texture": true,
        "tex_coord": 0.0,
        "is_locked": false,
        "editor_layer": 0,
        "editor_layer_name": "",
        "editor_layer_visibility": true
      },
      {
        "x": 241.8932,
        "y": 1812.9824,
        "z": 0.0,
        "smooth": true,
        "is_slingshot": false,
        "has_auto_texture": true,
        "tex_coord": 0.0,
        "is_locked": false,
        "editor_layer": 0,
        "editor_layer_name": "",
        "editor_layer_visibility": true
      },
      {
        "x": 241.89482,
        "y": 1809.2134,
        "z": 0.0,
        "smooth": false,
        "is_slingshot": false,
        "has_auto_texture": true,
        "tex_coord": 0.0,
        "is_locked": false,
        "editor_layer": 0,
        "editor_layer_name": "",
        "editor_layer_visibility": true
      },
      {
        "x": 240.0962,
        "y": 1805.7595,
        "z": 0.0,
        "smooth": false,
        "is_slingshot": true,
        "has_auto_texture": true,
        "tex_coord": 0.0,
        "is_locked": false,
        "editor_layer": 0,
        "editor_layer_name": "",
        "editor_layer_visibility": true
      }
    ]
  }
}