{
  "Light": {
    "center": {
      "x": 868.3641,
      "y": 513.89014
    },
    "height": 0.0,
    "falloff_radius": 40.0,
    "falloff_power": 2.0,
    "state_u32": 0,
    "state": 0.0,
    "color": "#008000",
    "color2": "#004000",
    "is_timer_enabled": false,
    "timer_interval": 100,
    "blink_pattern": "10",
    "off_image": "playfield-4k",
    "blink_interval": 125,
    "intensity": 2.0,
    "transmission_scale": 0.5,
    "surface": "",
    "name": "LText27",
    "is_backglass": false,
    "depth_bias": 0.0,
    "fade_speed_up": 0.2,
    "fade_speed_down": 0.2,
    "is_bulb_light": false,
    "is_image_mode": false,
    "show_bulb_mesh": false,
    "has_static_bulb_mesh": true,
    "show_reflection_on_ball": false,
    "mesh_radius": 20.0,
    "bulb_modulate_vs_add": 0.9,
    "bulb_halo_height": 28.0,
    "shadows": "none",
    "fader": "linear",
    "visible": true,
    "drag_points": [
      {
        "x": 855.0481,
        "y": 548.3978,
        "z": 0.0,
        "smooth": true,
        "is_slingshot": false,
        "has_auto_texture": true,
        "tex_coord": 0.0,
        "is_locked": false,
        "editor_layer": 0,
        "editor_layer_name": "",
        "editor_layer_visibility": true
      },
      {
        "x": 863.85376,
        "y": 550.06665,
        "z": 0.0,
        "smooth": true,
        "is_slingshot": false,
        "has_auto_texture": true,
        "tex_coord": 0.0,
        "is_locked": false,
        "editor_layer": 0,
        "editor_layer_name": "",
        "editor_layer_visibility": true
      },
      {
        "x": 870.9478,
        "y": 550.1235,
        "z": 0.0,
        "smooth": true,
        "is_slingshot": false,
        "has_auto_texture": true,
        "tex_coord": 0.0,
        "is_locked": false,
        "editor_layer": 0,
        "editor_layer_name": "",
        "editor_layer_visibility": true
      },
      {
        "x": 879.4518,
        "y": 550.1485,
        "z": 0.0,
        "smooth": true,
        "is_slingshot": false,
        "has_auto_texture": true,
        "tex_coord": 0.0,
        "is_locked": false,
        "editor_layer": 0,
        "editor_layer_name": "",
        "editor_layer_visibility": true
      },
      {
        "x": 886.9775,
        "y": 549.28644,
        "z": 0.0,
        "smooth": true,
        "is_slingshot": false,
        "has_auto_texture": true,
        "tex_coord": 0.0,
        "is_locked": false,
        "editor_layer": 0,
        "editor_layer_name": "",
        "editor_layer_visibility": true
      },
      {
        "x": 892.82074,
        "y": 546.37805,
        "z": 0.0,
        "smooth": true,
        "is_slingshot": false,
        "has_auto_texture": true,
        "tex_coord": 0.0,
        "is_locked": false,
        "editor_layer": 0,
        "editor_layer_name": "",
        "editor_layer_visibility": true
      },
      {
        "x": 895.56506,
        "y": 541.6877,
        "z": 0.0,
        "smooth": true,
        "is_slingshot": false,
        "has_auto_texture": true,
        "tex_coord": 0.0,
        "is_locked": false,
        "editor_layer": 0,
        "editor_layer_name": "",
        "editor_layer_visibility": true
      },
      {
        "x": 895.28357,
        "y": 532.7277,
        "z": 0.0,
        "smooth": true,
        "is_slingshot": false,
        "has_auto_texture": true,
        "tex_coord": 0.0,
        "is_locked": false,
        "editor_layer": 0,
        "editor_layer_name": "",
        "editor_layer_visibility": true
      },
      {
        "x": 892.34515,
        "y": 526.6092,
        "z": 0.0,
        "smooth": true,
        "is_slingshot": false,
        "has_auto_texture": true,
        "tex_coord": 0.0,
        "is_locked": false,
        "editor_layer": 0,
        "editor_layer_name": "",
        "editor_layer_visibility": true
      },
      {
        "x": 896.5104,
        "y": 523.5717,
        "z": 0.0,
        "smooth": true,
        "is_slingshot": false,
        "has_auto_texture": true,
        "tex_coord": 0.0,
        "is_locked": false,
        "editor_layer": 0,
        "editor_layer_name": "",
        "editor_layer_visibility": true
      },
      {
        "x": 900.1485,
        "y": 520.6773,
        "z": 0.0,
        "smooth": true,
        "is_slingshot": false,
        "has_auto_texture": true,
        "tex_coord": 0.0,
        "is_locked": false,
        "editor_layer": 0,
        "editor_layer_name": "",
        "editor_layer_visibility": true
      },
      {
        "x": 902.9533,
        "y": 516.91766,
        "z": 0.0,
        "smooth": true,
        "is_slingshot": false,
        "has_auto_texture": true,
        "tex_coord": 0.0,
        "is_locked": false,
        "editor_layer": 0,
        "editor_layer_name": "",
        "editor_layer_visibility": true
      },
      {
        "x": 904.51306,
        "y": 512.0493,
        "z": 0.0,
        "smooth": true,
        "is_slingshot": false,
        "has_auto_texture": true,
        "tex_coord": 0.0,
        "is_locked": false,
        "editor_layer": 0,
        "editor_layer_name": "",
        "editor_layer_visibility": true
      },
      {
        "x": 904.94336,
        "y": 507.57562,
        "z": 0.0,
        "smooth": false,
        "is_slingshot": true,
        "has_auto_texture": true,
        "tex_coord": 0.0,
        "is_locked": false,
        "editor_layer": 0,
        "editor_layer_name": "",
        "editor_layer_visibility": true
      },
      {
        "x": 904.0877,
        "y": 500.46484,
        "z": 0.0,
        "smooth": false,
        "is_slingshot": true,
        "has_auto_texture": true,
        "tex_coord": 0.0,
        "is_locked": false,
        "editor_layer": 0,
        "editor_layer_name": "",
        "editor_layer_visibility": true
      },
      {
        "x": 902.1005,
        "y": 494.24335,
        "z": 0.0,
        "smooth": false,
        "is_slingshot": true,
        "has_auto_texture": true,
        "tex_coord": 0.0,
        "is_locked": false,
        "editor_layer": 0,
        "editor_layer_name": "",
        "editor_layer_visibility": true
      },
      {
        "x": 899.01117,
        "y": 489.33603,
        "z": 0.0,
        "smooth": false,
        "is_slingshot": false,
        "has_auto_texture": true,
        "tex_coord": 0.0,
        "is_locked": false,
        "editor_layer": 0,
        "editor_layer_name": "",
        "editor_layer_visibility": true
      },
      {
        "x": 894.5382,
        "y": 486.38293,
        "z": 0.0,
        "smooth": true,
        "is_slingshot": false,
        "has_auto_texture": true,
        "tex_coord": 0.0,
        "is_locked": false,
        "editor_layer": 0,
        "editor_layer_name": "",
        "editor_layer_visibility": true
      },
      {
        "x": 889.33093,
        "y": 485.18994,
        "z": 0.0,
        "smooth": true,
        "is_slingshot": false,
        "has_auto_texture": true,
        "tex_coord": 0.0,
        "is_locked": false,
        "editor_layer": 0,
        "editor_layer_name": "",
        "editor_layer_visibility": true
      },
      {
        "x": 884.4208,
        "y": 484.82507,
        "z": 0.0,
        "smooth": true,
        "is_slingshot": false,
        "has_auto_texture": true,
        "tex_coord": 0.0,
        "is_locked": false,
        "editor_layer": 0,
        "editor_layer_name": "",
        "editor_layer_visibility": true
      },
      {
        "x": 878.2639,
        "y": 483.26288,
        "z": 0.0,
        "smooth": true,
        "is_slingshot": false,
        "has_auto_texture": true,
        "tex_coord": 0.0,
        "is_locked": false,
        "editor_layer": 0,
        "editor_layer_name": "",
        "editor_layer_visibility": true
      },
      {
        "x": 871.9877,
        "y": 481.28818,
        "z": 0.0,
        "smooth": true,
        "is_slingshot": false,
        "has_auto_texture": true,
        "tex_coord": 0.0,
        "is_locked": false,
        "editor_layer": 0,
        "editor_layer_name": "",
        "editor_layer_visibility": true
      },
      {
        "x": 866.2705,
        "y": 480.2687,
        "z": 0.0,
        "smooth": true,
        "is_slingshot": false,
        "has_auto_texture": true,
        "tex_coord": 0.0,
        "is_locked": false,
        "editor_layer": 0,
        "editor_layer_name": "",
        "editor_layer_visibility": true
      },
      {
        "x": 859.9012,
        "y": 479.51154,
        "z": 0.0,
        "smooth": true,
        "is_slingshot": false,
        "has_auto_texture": true,
        "tex_coord": 0.0,
        "is_locked": false,
        "editor_layer": 0,
        "editor_layer_name": "",
        "editor_layer_visibility": true
      },
      {
        "x": 852.2767,
        "y": 479.4458,
        "z": 0.0,
        "smooth": true,
        "is_slingshot": false,
        "has_auto_texture": true,
        "tex_coord": 0.0,
        "is_locked": false,
        "editor_layer": 0,
        "editor_layer_name": "",
        "editor_layer_visibility": true
      },
      {
        "x": 845.54016,
        "y": 481.25714,
        "z": 0.0,
        "smooth": true,
        "is_slingshot": false,
        "has_auto_texture": true,
        "tex_coord": 0.0,
        "is_locked": false,
        "editor_layer": 0,
        "editor_layer_name": "",
        "editor_layer_visibility": true
      },
      {
        "x": 840.6045,
        "y": 483.88824,
        "z": 0.0,
        "smooth": true,
        "is_slingshot": false,
        "has_auto_texture": true,
        "tex_coord": 0.0,
        "is_locked": false,
        "editor_layer": 0,
        "editor_layer_name": "",
        "editor_layer_visibility": true
      },
      {
        "x": 836.9358,
        "y": 490.2114,
        "z": 0.0,
        "smooth": true,
        "is_slingshot": false,
        "has_auto_texture": true,
        "tex_coord": 0.0,
        "is_locked": false,
        "editor_layer": 0,
        "editor_layer_name": "",
        "editor_layer_visibility": true
      },
      {
        "x": 836.2372,
        "y": 496.69598,
        "z": 0.0,
        "smooth": true,
        "is_slingshot": false,
        "has_auto_texture": true,
        "tex_coord": 0.0,
        "is_locked": false,
        "editor_layer": 0,
        "editor_layer_name": "",
        "editor_layer_visibility": true
      },
      {
        "x": 837.7562,
        "y": 501.99304,
        "z": 0.0,
        "smooth": true,
        "is_slingshot": false,
        "has_auto_texture": true,
        "tex_coord": 0.0,
        "is_locked": false,
        "editor_layer": 0,
        "editor_layer_name": "",
        "editor_layer_visibility": true
      },
      {
        "x": 835.1759,
        "y": 509.0919,
        "z": 0.0,
        "smooth": true,
        "is_slingshot": false,
        "has_auto_texture": true,
        "tex_coord": 0.0,
        "is_locked": false,
        "editor_layer": 0,
        "editor_layer_name": "",
        "editor_layer_visibility": true
      },
      {
        "x": 833.5438,
        "y": 514.55945,
        "z": 0.0,
        "smooth": true,
        "is_slingshot": false,
        "has_auto_texture": true,
        "tex_coord": 0.0,
        "is_locked": false,
        "editor_layer": 0,
        "editor_layer_name": "",
        "editor_layer_visibility": true
      },
      {
        "x": 832.833,
        "y": 521.8388,
        "z": 0.0,
        "smooth": true,
        "is_slingshot": false,
        "has_auto_texture": true,
        "tex_coord": 0.0,
        "is_locked": false,
        "editor_layer": 0,
        "editor_layer_name": "",
        "editor_layer_visibility": true
      },
      {
        "x": 832.7261,
        "y": 528.47046,
        "z": 0.0,
        "smooth": true,
        "is_slingshot": false,
        "has_auto_texture": true,
        "tex_coord": 0.0,
        "is_locked": false,
        "editor_layer": 0,
        "editor_layer_name": "",
        "editor_layer_visibility": true
      },
      {
        "x": 833.22595,
        "y": 533.40063,
        "z": 0.0,
        "smooth": true,
        "is_slingshot": false,
        "has_auto_texture": true,
        "tex_coord": 0.0,
        "is_locked": false,
        "editor_layer": 0,
        "editor_layer_name": "",
        "editor_layer_visibility": true
      },
      {
        "x": 834.83026,
        "y": 538.2823,
        "z": 0.0,
        "smooth": true,
        "is_slingshot": false,
        "has_auto_texture": true,
        "tex_coord": 0.0,
        "is_locked": false,
        "editor_layer": 0,
        "editor_layer_name": "",
        "editor_layer_visibility": true
      },
      {
        "x": 838.244,
        "y": 541.8012,
        "z": 0.0,
        "smooth": true,
        "is_slingshot": false,
        "has_auto_texture": true,
        "tex_coord": 0.0,
        "is_locked": false,
        "editor_layer": 0,
        "editor_layer_name": "",
        "editor_layer_visibility": true
      },
      {
        "x": 843.6487,
        "y": 544.78394,
        "z": 0.0,
        "smooth": true,
        "is_slingshot": false,
        "has_auto_texture": true,
        "tex_coord": 0.0,
        "is_locked": false,
        "editor_layer": 0,
        "editor_layer_name": "",
        "editor_layer_visibility": true
      },
      {
        "x": 849.3628,
        "y": 546.6045,
        "z": 0.0,
        "smooth": true,
        "is_slingshot": false,
        "has_auto_texture": true,
        "tex_coord": 0.0,
        "is_locked": false,
        "editor_layer": 0,
        "editor_layer_name": "",
        "editor_layer_visibility": true
      }
    ]
  }
}